aaapi/AudioUtils.py
aaapi/MidiUtils.py
aaapi/MusicUtils.py
aaapi/__init__.py
aaapi/aaapi.py
aaapi-0.1.1.dist-info/AUTHORS.rst
aaapi-0.1.1.dist-info/LICENSE
aaapi-0.1.1.dist-info/METADATA
aaapi-0.1.1.dist-info/WHEEL
aaapi-0.1.1.dist-info/top_level.txt
aaapi-0.1.1.dist-info/RECORD
