Metadata-Version: 2.1
Name: aaapi
Version: 0.1.1
Summary: Another Audio API - Collection of audio and music processing API with massive amount of dependencies
Home-page: https://github.com/ye-yu/aaapi
Author: Ye Yu
Author-email: rafolwen98@gmail.com
License: MIT license
Keywords: aaapi
Platform: UNKNOWN
Classifier: Development Status :: 2 - Pre-Alpha
Classifier: Intended Audience :: Developers
Classifier: License :: OSI Approved :: MIT License
Classifier: Natural Language :: English
Classifier: Programming Language :: Python :: 3.6
Classifier: Programming Language :: Python :: 3.7
Classifier: Programming Language :: Python :: 3.8
Requires-Python: >=3.6
Requires-Dist: crepe
Requires-Dist: pandas
Requires-Dist: scikit-learn (==0.22)
Requires-Dist: scipy
Requires-Dist: librosa
Requires-Dist: mido
Requires-Dist: numpy
